AUTHORS
LICENSE
MANIFEST.in
README.rst
setup.py
panya_post.egg-info/PKG-INFO
panya_post.egg-info/SOURCES.txt
panya_post.egg-info/dependency_links.txt
panya_post.egg-info/not-zip-safe
panya_post.egg-info/requires.txt
panya_post.egg-info/top_level.txt
post/__init__.py
post/admin.py
post/generator.py
post/models.py
post/urls.py
post/views.py
post/fixtures/photosizes.json
post/templates/post/post_detail.html
post/templates/post/post_list.html
post/templates/post/inclusion_tags/post_detail.html
post/templatetags/__init__.py
post/templatetags/post_inclusion_tags.py